Metadata-Version: 2.1
Name: streamingpackagetyler3
Version: 0.2.0
Summary: streaming python package
Home-page: https://github.com/huangyue1752/Streaming_Function.git
Author: Tyler Huang
Author-email: huangyue1752@gmail.com
License: UNKNOWN
Platform: UNKNOWN
Classifier: Programming Language :: Python :: 3
Classifier: License :: OSI Approved :: MIT License
Classifier: Operating System :: OS Independent
Requires-Python: >=3.9
